parade/__init__.py
parade/command/check.py
parade/command/check.pyi
parade_check-0.0.1.6.dist-info/LICENSE
parade_check-0.0.1.6.dist-info/METADATA
parade_check-0.0.1.6.dist-info/WHEEL
parade_check-0.0.1.6.dist-info/top_level.txt
parade_check-0.0.1.6.dist-info/RECORD
