Metadata-Version: 2.1
Name: parade-check
Version: 0.0.1.6
Summary: A check module of parade
Home-page: https://github.com/cpzt/parade-check
Author: Pan Chen
Author-email: chenpan9012@gmail.com
Platform: any
Classifier: Intended Audience :: Developers
Classifier: License :: OSI Approved :: Apache Software License
Classifier: Programming Language :: Python :: 3
Classifier: Topic :: Database
Classifier: Topic :: Software Development :: Libraries :: Python Modules
Classifier: Operating System :: Unix
Classifier: Operating System :: MacOS :: MacOS X
Classifier: Operating System :: Microsoft :: Windows
Classifier: Operating System :: POSIX
Requires-Python: >=3.4
License-File: LICENSE
Requires-Dist: parade
